[
    {
        "date":"5\/17\/2022",
        "cases":"1",
        "cumulative_sum":1
    },
    {
        "date":"5\/18\/2022",
        "cases":"0",
        "cumulative_sum":1
    },
    {
        "date":"5\/19\/2022",
        "cases":"0",
        "cumulative_sum":1
    },
    {
        "date":"5\/20\/2022",
        "cases":"1",
        "cumulative_sum":2
    },
    {
        "date":"5\/21\/2022",
        "cases":"2",
        "cumulative_sum":4
    },
    {
        "date":"5\/22\/2022",
        "cases":"1",
        "cumulative_sum":5
    },
    {
        "date":"5\/23\/2022",
        "cases":"3",
        "cumulative_sum":8
    },
    {
        "date":"5\/24\/2022",
        "cases":"1",
        "cumulative_sum":9
    },
    {
        "date":"5\/25\/2022",
        "cases":"1",
        "cumulative_sum":10
    },
    {
        "date":"5\/26\/2022",
        "cases":"1",
        "cumulative_sum":11
    },
    {
        "date":"5\/27\/2022",
        "cases":"3",
        "cumulative_sum":14
    },
    {
        "date":"5\/28\/2022",
        "cases":"0",
        "cumulative_sum":14
    },
    {
        "date":"5\/29\/2022",
        "cases":"1",
        "cumulative_sum":15
    },
    {
        "date":"5\/30\/2022",
        "cases":"0",
        "cumulative_sum":15
    },
    {
        "date":"5\/31\/2022",
        "cases":"4",
        "cumulative_sum":19
    },
    {
        "date":"6\/1\/2022",
        "cases":"1",
        "cumulative_sum":20
    },
    {
        "date":"6\/2\/2022",
        "cases":"3",
        "cumulative_sum":23
    },
    {
        "date":"6\/3\/2022",
        "cases":"5",
        "cumulative_sum":28
    },
    {
        "date":"6\/4\/2022",
        "cases":"1",
        "cumulative_sum":29
    },
    {
        "date":"6\/5\/2022",
        "cases":"0",
        "cumulative_sum":29
    },
    {
        "date":"6\/6\/2022",
        "cases":"5",
        "cumulative_sum":34
    },
    {
        "date":"6\/7\/2022",
        "cases":"4",
        "cumulative_sum":38
    },
    {
        "date":"6\/8\/2022",
        "cases":"5",
        "cumulative_sum":43
    },
    {
        "date":"6\/9\/2022",
        "cases":"7",
        "cumulative_sum":50
    },
    {
        "date":"6\/10\/2022",
        "cases":"5",
        "cumulative_sum":55
    },
    {
        "date":"6\/11\/2022",
        "cases":"2",
        "cumulative_sum":57
    },
    {
        "date":"6\/12\/2022",
        "cases":"5",
        "cumulative_sum":62
    },
    {
        "date":"6\/13\/2022",
        "cases":"3",
        "cumulative_sum":65
    },
    {
        "date":"6\/14\/2022",
        "cases":"16",
        "cumulative_sum":81
    },
    {
        "date":"6\/15\/2022",
        "cases":"8",
        "cumulative_sum":89
    },
    {
        "date":"6\/16\/2022",
        "cases":"16",
        "cumulative_sum":105
    },
    {
        "date":"6\/17\/2022",
        "cases":"8",
        "cumulative_sum":113
    },
    {
        "date":"6\/18\/2022",
        "cases":"9",
        "cumulative_sum":122
    },
    {
        "date":"6\/19\/2022",
        "cases":"4",
        "cumulative_sum":126
    },
    {
        "date":"6\/20\/2022",
        "cases":"11",
        "cumulative_sum":137
    },
    {
        "date":"6\/21\/2022",
        "cases":"14",
        "cumulative_sum":151
    },
    {
        "date":"6\/22\/2022",
        "cases":"19",
        "cumulative_sum":170
    },
    {
        "date":"6\/23\/2022",
        "cases":"18",
        "cumulative_sum":188
    },
    {
        "date":"6\/24\/2022",
        "cases":"42",
        "cumulative_sum":230
    },
    {
        "date":"6\/25\/2022",
        "cases":"12",
        "cumulative_sum":242
    },
    {
        "date":"6\/26\/2022",
        "cases":"9",
        "cumulative_sum":251
    },
    {
        "date":"6\/27\/2022",
        "cases":"60",
        "cumulative_sum":311
    },
    {
        "date":"6\/28\/2022",
        "cases":"40",
        "cumulative_sum":351
    },
    {
        "date":"6\/29\/2022",
        "cases":"44",
        "cumulative_sum":395
    },
    {
        "date":"6\/30\/2022",
        "cases":"56",
        "cumulative_sum":451
    },
    {
        "date":"7\/1\/2022",
        "cases":"55",
        "cumulative_sum":506
    },
    {
        "date":"7\/2\/2022",
        "cases":"15",
        "cumulative_sum":521
    },
    {
        "date":"7\/3\/2022",
        "cases":"9",
        "cumulative_sum":530
    },
    {
        "date":"7\/4\/2022",
        "cases":"25",
        "cumulative_sum":555
    },
    {
        "date":"7\/5\/2022",
        "cases":"37",
        "cumulative_sum":592
    },
    {
        "date":"7\/6\/2022",
        "cases":"48",
        "cumulative_sum":640
    },
    {
        "date":"7\/7\/2022",
        "cases":"54",
        "cumulative_sum":694
    },
    {
        "date":"7\/8\/2022",
        "cases":"44",
        "cumulative_sum":738
    },
    {
        "date":"7\/9\/2022",
        "cases":"41",
        "cumulative_sum":779
    },
    {
        "date":"7\/10\/2022",
        "cases":"10",
        "cumulative_sum":789
    },
    {
        "date":"7\/11\/2022",
        "cases":"97",
        "cumulative_sum":886
    },
    {
        "date":"7\/12\/2022",
        "cases":"164",
        "cumulative_sum":1050
    },
    {
        "date":"7\/13\/2022",
        "cases":"150",
        "cumulative_sum":1200
    },
    {
        "date":"7\/14\/2022",
        "cases":"216",
        "cumulative_sum":1416
    },
    {
        "date":"7\/15\/2022",
        "cases":"172",
        "cumulative_sum":1588
    },
    {
        "date":"7\/16\/2022",
        "cases":"10",
        "cumulative_sum":1598
    },
    {
        "date":"7\/17\/2022",
        "cases":"7",
        "cumulative_sum":1605
    },
    {
        "date":"7\/18\/2022",
        "cases":"183",
        "cumulative_sum":1788
    },
    {
        "date":"7\/19\/2022",
        "cases":"294",
        "cumulative_sum":2082
    },
    {
        "date":"7\/20\/2022",
        "cases":"183",
        "cumulative_sum":2265
    },
    {
        "date":"7\/21\/2022",
        "cases":"169",
        "cumulative_sum":2434
    },
    {
        "date":"7\/22\/2022",
        "cases":"317",
        "cumulative_sum":2751
    },
    {
        "date":"7\/23\/2022",
        "cases":"22",
        "cumulative_sum":2773
    },
    {
        "date":"7\/24\/2022",
        "cases":"12",
        "cumulative_sum":2785
    },
    {
        "date":"7\/25\/2022",
        "cases":"752",
        "cumulative_sum":3537
    },
    {
        "date":"7\/26\/2022",
        "cases":"622",
        "cumulative_sum":4159
    },
    {
        "date":"7\/27\/2022",
        "cases":"476",
        "cumulative_sum":4635
    },
    {
        "date":"7\/28\/2022",
        "cases":"187",
        "cumulative_sum":4822
    },
    {
        "date":"7\/29\/2022",
        "cases":"437",
        "cumulative_sum":5259
    },
    {
        "date":"7\/30\/2022",
        "cases":"25",
        "cumulative_sum":5284
    },
    {
        "date":"7\/31\/2022",
        "cases":"21",
        "cumulative_sum":5305
    },
    {
        "date":"8\/1\/2022",
        "cases":"543",
        "cumulative_sum":5848
    },
    {
        "date":"8\/2\/2022",
        "cases":"527",
        "cumulative_sum":6375
    },
    {
        "date":"8\/3\/2022",
        "cases":"289",
        "cumulative_sum":6664
    },
    {
        "date":"8\/4\/2022",
        "cases":"443",
        "cumulative_sum":7107
    },
    {
        "date":"8\/5\/2022",
        "cases":"432",
        "cumulative_sum":7539
    },
    {
        "date":"8\/6\/2022",
        "cases":"33",
        "cumulative_sum":7572
    },
    {
        "date":"8\/7\/2022",
        "cases":"10",
        "cumulative_sum":7582
    },
    {
        "date":"8\/8\/2022",
        "cases":"868",
        "cumulative_sum":8450
    },
    {
        "date":"8\/9\/2022",
        "cases":"522",
        "cumulative_sum":8972
    },
    {
        "date":"8\/10\/2022",
        "cases":"1391",
        "cumulative_sum":10363
    }
]